secretflow_doctools/__init__.py
secretflow_doctools/__main__.py
secretflow_doctools/builder.py
secretflow_doctools/l10n.py
secretflow_doctools/options.py
secretflow_doctools/pathfinding.py
secretflow_doctools/server.py
secretflow_doctools/sidebar.py
secretflow_doctools/translator.py
secretflow_doctools/vcs.py
secretflow_doctools/cmd/__init__.py
secretflow_doctools/cmd/build.py
secretflow_doctools/cmd/clean.py
secretflow_doctools/cmd/preview.py
secretflow_doctools/cmd/publish.py
secretflow_doctools/cmd/update_translations.py
secretflow_doctools/cmd/util.py
secretflow_doctools/i18n/__init__.py
secretflow_doctools/i18n/builder.py
secretflow_doctools/i18n/json.py
secretflow_doctools/js/.gitignore
secretflow_doctools/js/__init__.py
secretflow_doctools/js/cli.js
secretflow_doctools/js/cli.py
secretflow_doctools/js/package.json
secretflow_doctools/js/web.tar
secretflow_doctools/locales/.gitignore
secretflow_doctools/locales/messages.pot
secretflow_doctools/locales/zh_CN/LC_MESSAGES/messages.mo
secretflow_doctools/locales/zh_CN/LC_MESSAGES/messages.po
secretflow_doctools/markdown/__init__.py
secretflow_doctools/markdown/ffi.py
secretflow_doctools/markdown/utils.py
secretflow_doctools/markdown/specs/__init__.py
secretflow_doctools/markdown/specs/content_model.py
secretflow_doctools/markdown/specs/directive.py
secretflow_doctools/markdown/specs/math.py
secretflow_doctools/markdown/specs/mdast.py
secretflow_doctools/markdown/specs/mdx.py
secretflow_doctools/markdown/specs/unist.py
secretflow_doctools/utils/__init__.py
secretflow_doctools/utils/logging.py
secretflow_doctools/utils/subprocess.py
secretflow_doctools-0.8.5.data/scripts/secretflow-doctools-js-cli
secretflow_doctools-0.8.5.dist-info/METADATA
secretflow_doctools-0.8.5.dist-info/WHEEL
secretflow_doctools-0.8.5.dist-info/entry_points.txt
secretflow_doctools-0.8.5.dist-info/licenses/LICENSE
secretflow_doctools-0.8.5.dist-info/RECORD
