Metadata-Version: 2.4
Name: secretflow-doctools
Version: 0.8.5
Summary: Documentation builder for SecretFlow
Project-URL: Documentation, https://github.com/secretflow/doctools/blob/main/CONTRIBUTING.md
Project-URL: Issues, https://github.com/secretflow/doctools/issues
Project-URL: Repository, https://github.com/secretflow/doctools
Author-email: SecretFlow Team <secretflow-contact@service.alipay.com>
License-Expression: Apache-2.0
License-File: LICENSE
Requires-Python: >=3.10
Requires-Dist: ansi2html~=1.9
Requires-Dist: flask~=3.1
Requires-Dist: loguru~=0.7
Requires-Dist: more-itertools~=10.6
Requires-Dist: myst-parser~=4.0
Requires-Dist: pexpect~=4.9
Requires-Dist: pydantic-settings~=2.8
Requires-Dist: pydantic~=2.6
Requires-Dist: requests~=2.32
Requires-Dist: ruamel-yaml~=0.18
Requires-Dist: sphinx-intl~=2.3
Requires-Dist: sphinx~=8.0
Requires-Dist: thefuzz~=0.22.1
